proxy/__init__.py
proxy/__main__.py
proxy/proxy.py
proxy/utils.py
terminal_proxy-0.2.0.dist-info/LICENSE
terminal_proxy-0.2.0.dist-info/METADATA
terminal_proxy-0.2.0.dist-info/WHEEL
terminal_proxy-0.2.0.dist-info/entry_points.txt
terminal_proxy-0.2.0.dist-info/top_level.txt
terminal_proxy-0.2.0.dist-info/RECORD
