Metadata-Version: 2.1
Name: terminal-proxy
Version: 0.2.0
Summary: Proxy management tool for terminal.
Home-page: https://github.com/Prodesire/terminal-proxy
Author: Prodesire
Author-email: wangbinxin001@126.com
License: MIT License
Platform: UNKNOWN
Classifier: Operating System :: OS Independent
Classifier: Intended Audience :: Developers
Classifier: License :: OSI Approved :: MIT License
Classifier: Programming Language :: Python
Classifier: Programming Language :: Python :: Implementation
Classifier: Programming Language :: Python :: 2
Classifier: Programming Language :: Python :: 2.7
Classifier: Programming Language :: Python :: 3
Classifier: Programming Language :: Python :: 3.5
Classifier: Programming Language :: Python :: 3.6
Classifier: Programming Language :: Python :: 3.7
Classifier: Programming Language :: Python :: 3.8
Classifier: Topic :: Software Development :: Libraries
Requires-Dist: click (>=0.7.0)
Requires-Dist: colorama (>=0.4.3)
